numprimo_miguel_redondo/__init__.py
numprimo_miguel_redondo-1.0.dist-info/LICENSE
numprimo_miguel_redondo-1.0.dist-info/METADATA
numprimo_miguel_redondo-1.0.dist-info/WHEEL
numprimo_miguel_redondo-1.0.dist-info/top_level.txt
numprimo_miguel_redondo-1.0.dist-info/RECORD
